complexity_estimate/Algorythms.py
complexity_estimate/ComplexCalc.py
complexity_estimate/Timeout.py
complexity_estimate/UsageException.py
complexity_estimate/__init__.py
complexity_estimate/main.py
complexity_estimate-1.0.dist-info/DESCRIPTION.rst
complexity_estimate-1.0.dist-info/METADATA
complexity_estimate-1.0.dist-info/RECORD
complexity_estimate-1.0.dist-info/WHEEL
complexity_estimate-1.0.dist-info/metadata.json
complexity_estimate-1.0.dist-info/top_level.txt
