Metadata-Version: 2.0
Name: complexity-estimate
Version: 1.0
Summary: Project allowing estimating complexity of algorythms using lists and time for given size and vice versa.
Home-page: https://github.com/AGHPythonCourse2017/zad2-chudy1997
Author: Karol Bartyzel
Author-email: karolbartyzel308@gmail.com
License: Freeware
Platform: UNKNOWN
